qucochemistry/__init__.py
qucochemistry/_version.py
qucochemistry/circuits.py
qucochemistry/utils.py
qucochemistry/vqe.py
qucochemistry-0.1.2.dist-info/LICENSE
qucochemistry-0.1.2.dist-info/METADATA
qucochemistry-0.1.2.dist-info/WHEEL
qucochemistry-0.1.2.dist-info/top_level.txt
qucochemistry-0.1.2.dist-info/RECORD
