Metadata-Version: 2.1
Name: qucochemistry
Version: 0.1.2
Summary: A VQE package which interfaces with Rigetti's QCS platform
Home-page: UNKNOWN
Author: Vincent Elfving
Author-email: quantumcode@quandco.com
License: Apache 2
Platform: UNKNOWN
Classifier: Programming Language :: Python :: 3.6
Classifier: Programming Language :: Python :: 3.7
Classifier: Programming Language :: Python :: 3.8
Classifier: License :: OSI Approved :: Apache Software License
Classifier: Operating System :: OS Independent
Requires-Python: >=3.6
Requires-Dist: openfermion (==0.10.0)
Requires-Dist: pyquil (<=2.24.0,>=2.16.0)
